{"nodes": [{"id": "sap_api_app", "label": "sap-api/app.py", "file_type": "code", "source_file": "services/sap-api/app.py", "source_location": null, "source_url": null, "captured_at": null, "author": null, "contributor": null}], "edges": [{"source": "sap_api_app", "target": "sap_data_generator", "relation": "calls", "confidence": "EXTRACTED", "confidence_score": 1.0, "source_file": "services/sap-api/app.py", "source_location": "L18", "weight": 1.0}, {"source": "sap_api_app", "target": "sap_vendor_data", "relation": "shares_data_with", "confidence": "EXTRACTED", "confidence_score": 1.0, "source_file": "services/sap-api/app.py", "source_location": "L23", "weight": 1.0}], "hyperedges": []}